kapao_pytorch/__init__.py
kapao_pytorch/kapao_pytorch.py
kapao_pytorch-0.1.1.dist-info/METADATA
kapao_pytorch-0.1.1.dist-info/WHEEL
kapao_pytorch-0.1.1.dist-info/top_level.txt
kapao_pytorch-0.1.1.dist-info/RECORD
