Metadata-Version: 2.1
Name: kapao-pytorch
Version: 0.1.1
Summary: PoseEstimation
Home-page: https://github.com/abhigoku10/kapao-pytorch
Author: abhigoku10
Author-email: abhigoku10@gmail.com
License: UNKNOWN
Platform: UNKNOWN
Classifier: Programming Language :: Python :: 3
Classifier: License :: OSI Approved :: MIT License
Classifier: Operating System :: OS Independent
